DP_epidemiology/__init__.py
DP_epidemiology/contact_matrix.py
DP_epidemiology/hotspot_analyzer.py
DP_epidemiology/mobility_analyzer.py
DP_epidemiology/pandemic_adherence_analyzer.py
DP_epidemiology/utilities.py
DP_epidemiology/viz.py
dp_epidemiology-0.1.1.dist-info/METADATA
dp_epidemiology-0.1.1.dist-info/WHEEL
dp_epidemiology-0.1.1.dist-info/licenses/LICENSE
dp_epidemiology-0.1.1.dist-info/RECORD
