Metadata-Version: 2.3
Name: DP_epidemiology
Version: 0.1.1
Summary: A package for differential private release of fianancial data in context of epidemiology
Project-URL: Homepage, https://pets-for-public-health-challenge.readthedocs.io/en/latest/
Project-URL: repository, https://github.com/KnowledgeEdgeAI/PETs_for_Public_Health_Challenge/tree/main
Author-email: Shubham Kumar <sk834rk@gmail.com>, Milan Anand Raj <milananandraj1502@gmail.com>, Divya Gupta <divygupt2002@gmail.com>
Classifier: License :: OSI Approved :: MIT License
Classifier: Operating System :: OS Independent
Classifier: Programming Language :: Python :: 3
Requires-Python: >=3.10
Requires-Dist: antlr4-python3-runtime==4.13.2
Requires-Dist: dash
Requires-Dist: dtw
Requires-Dist: matplotlib
Requires-Dist: msrest==0.7.1
Requires-Dist: nbformat
Requires-Dist: numpy>=1.26.4
Requires-Dist: opendp==0.11.1
Requires-Dist: pandas>=2.1.4
Requires-Dist: plotly
Requires-Dist: scipy
Provides-Extra: dev
Requires-Dist: pytest; extra == 'dev'
